ngsPETSc/__init__.py
ngsPETSc/eps.py
ngsPETSc/ksp.py
ngsPETSc/mat.py
ngsPETSc/nullspace.py
ngsPETSc/pc.py
ngsPETSc/plex.py
ngsPETSc/snes.py
ngsPETSc/utils/__init__.py
ngsPETSc/utils/fenicsx.py
ngsPETSc/utils/firedrake/__init__.py
ngsPETSc/utils/firedrake/hierarchies.py
ngsPETSc/utils/firedrake/meshes.py
ngsPETSc/utils/ngs/__init__.py
ngsPETSc/utils/utils.py
ngsPETSc/vec.py
ngspetsc-0.1.1.dist-info/METADATA
ngspetsc-0.1.1.dist-info/WHEEL
ngspetsc-0.1.1.dist-info/licenses/LICENSE.txt
ngspetsc-0.1.1.dist-info/RECORD
