Metadata-Version: 2.4
Name: ngsPETSc
Version: 0.1.1
Summary: NGSolve/Netgen interface to PETSc
License-Expression: MIT
License-File: LICENSE.txt
Author: Umberto Zerbinati
Author-email: umberto.zerbinati@maths.ox.ac.uk
Maintainer: Umberto Zerbinati
Maintainer-email: umberto.zerbinati@maths.ox.ac.uk
Requires-Python: >=3.10,<4.0
Classifier: Programming Language :: Python :: 3
Classifier: License :: OSI Approved :: MIT License
Classifier: Operating System :: OS Independent
Classifier: Development Status :: 3 - Alpha
Provides-Extra: firedrake
Requires-Dist: firedrake ; extra == "firedrake"
Requires-Dist: netgen-mesher (>=6.2,<7.0)
Requires-Dist: netgen-occt (>=7.8,<8.0)
Requires-Dist: numpy (>=2,<3)
Requires-Dist: petsc4py (>=3.22,<4.0)
Requires-Dist: scipy (>=1,<2)
Project-URL: Documentation, https://ngspetsc.readthedocs.io/en/latest/
Project-URL: Repository, https://github.com/NGSolve/ngsPETSc
